getbstacksinfo/README.MD
getbstacksinfo/__init__.py
getbstacksinfo/lookup2.py
getbstacksinfo/requirements.txt
getbstacksinfo/thirdparty.json
getbstacksinfo-0.12.dist-info/LICENSE.rst
getbstacksinfo-0.12.dist-info/METADATA
getbstacksinfo-0.12.dist-info/WHEEL
getbstacksinfo-0.12.dist-info/top_level.txt
getbstacksinfo-0.12.dist-info/RECORD
