Metadata-Version: 2.1
Name: getbstacksinfo
Version: 0.12
Summary: Some useful Bluestacks stuff
Home-page: https://github.com/hansalemaos/getbstacksinfo
Author: Johannes Fischer
Author-email: aulasparticularesdealemaosp@gmail.com
License: MIT
Keywords: utils,Bluestacks
Classifier: Development Status :: 4 - Beta
Classifier: Programming Language :: Python :: 3 :: Only
Classifier: Programming Language :: Python :: 3.10
Classifier: Topic :: Software Development :: Libraries :: Python Modules
Classifier: Topic :: Utilities
License-File: LICENSE.rst
Requires-Dist: ctypes-window-info
Requires-Dist: list-all-files-recursively
Requires-Dist: nodepsutils
Requires-Dist: pidconnectioninfos
Requires-Dist: regex
Requires-Dist: regex4numbers
Requires-Dist: reggisearch
Requires-Dist: tkkillablethreads
